Workbook
Name Slicer_net_salary: #N/A

Sheet employee_master
A1: employee ID | B1: Employee Name | C1: department | D1: designantion | E1: joining date | F1: basic salary | G1: bank account | H1: pan number
A2: EMP001 | B2: RAJIV | C2: Human Resources (HR) | D2: Chief Executive Officer (CEO) | E2: 43831 | F2: 85000 | G2: 2544482525 | H2: ABCDE1234F
A3: EMP002 | B3: NAGA | C3: Finance & Accounting | D3: Human Resources Manager | E3: 43905 | F3: 62500 | G3: 2548662588 | H3: FGHIJ5678K
A4: EMP003 | B4: WASIF | C4: Information Technology (IT) | D4: Software Engineer | E4: 43992 | F4: 45000 | G4: 2578931456 | H4: LMNOP9012Q
A5: EMP004 | B5: RAJA | C5: Sales | D5: Financial Analyst | E5: 44065 | F5: 120000 | G5: 4458976235 | H5: RSTUV3456W
A6: EMP005 | B6: RAVI NAVI | C6: Marketing | D6: Marketing Coordinator | E6: 44140 | F6: 55000 | G6: 2458016897 | H6: XYZAB7890C
A7: EMP006 | B7: SHREE | C7: Operations | D7: Operations Director | E7: 44208 | F7: 78000 | G7: 1458932147 | H7: DEFGH2345I
A8: EMP007 | B8: KALESH | C8: Customer Support | D8: Project Manager | E8: 44255 | F8: 35000 | G8: 2587634954 | H8: JKLMN6789O
A9: EMP008 | B9: KHAANI | C9: Research & Development (R&D) | D9: Data Scientist | E9: 44335 | F9: 95000 | G9: 2589675123 | H9: PQRST0123U
A10: EMP009 | B10: SHRIBA | C10: Legal & Compliance | D10: Sales Representative | E10: 44380 | F10: 50000 | G10: 2548763254 | H10: VWXYZ4567A
A11: EMP010 | B11: MEDHA | C11: Supply Chain & Logistics | D11: Product Designer | E11: 44453 | F11: 68000 | G11: 2548963254 | H11: BCDEF8901G
A12: EMP011 | B12: SHRIVANI | C12: Product Management | D12: Customer Success Specialist | E12: 44531 | F12: 110000 | G12: 2158776958 | H12: HIJKL2345M
A13: EMP012 | B13: RAANI | C13: Quality Assurance (QA) | D13: Systems Administrator | E13: 44581 | F13: 42000 | G13: 2255896314 | H13: NOPQR6789S
... A16: EMP015 | B16: MAYUR | C16: Administration / Facilities | D16: Business Development Executive | E16: 44791 | F16: 89000 | G16: 1258975663 | H16: FGHIJ8901K

Sheet Attendance
A1: employee id | B1: employee name | C1: total working days | D1: present days | E1: leave days | F1: overtime hours
A2: EMP001 | B2: RAJIV | C2: 26 | D2: 24 | E2: =C2-D2 -> 2 | F2: 5
A3: EMP002 | B3: =VLOOKUP(A3,employee_master!A:B,2,FALSE) -> NAGA | C3: 26 | D3: 21 | E3: =C3-D3 -> 5 | F3: 2
A4: EMP003 | B4: =VLOOKUP(A4,employee_master!A:B,2,FALSE) -> WASIF | C4: 26 | D4: 26 | E4: =C4-D4 -> 0 | F4: 10
A5: EMP004 | B5: =VLOOKUP(A5,employee_master!A:B,2,FALSE) -> RAJA | C5: 26 | D5: 20 | E5: =C5-D5 -> 6 | F5: 2
A6: EMP005 | B6: =VLOOKUP(A6,employee_master!A:B,2,FALSE) -> RAVI NAVI | C6: 26 | D6: 22 | E6: =C6-D6 -> 4 | F6: 12
A7: EMP006 | B7: =VLOOKUP(A7,employee_master!A:B,2,FALSE) -> SHREE | C7: 26 | D7: 21 | E7: =C7-D7 -> 5 | F7: 6
A8: EMP007 | B8: =VLOOKUP(A8,employee_master!A:B,2,FALSE) -> KALESH | C8: 26 | D8: 22 | E8: =C8-D8 -> 4 | F8: 3
A9: EMP008 | B9: =VLOOKUP(A9,employee_master!A:B,2,FALSE) -> KHAANI | C9: 26 | D9: 20 | E9: =C9-D9 -> 6 | F9: 7
A10: EMP009 | B10: =VLOOKUP(A10,employee_master!A:B,2,FALSE) -> SHRIBA | C10: 26 | D10: 26 | E10: =C10-D10 -> 0 | F10: 6
A11: EMP010 | B11: =VLOOKUP(A11,employee_master!A:B,2,FALSE) -> MEDHA | C11: 26 | D11: 25 | E11: =C11-D11 -> 1 | F11: 10
A12: EMP011 | B12: =VLOOKUP(A12,employee_master!A:B,2,FALSE) -> SHRIVANI | C12: 26 | D12: 24 | E12: =C12-D12 -> 2 | F12: 8
A13: EMP012 | B13: =VLOOKUP(A13,employee_master!A:B,2,FALSE) -> RAANI | C13: 26 | D13: 24 | E13: =C13-D13 -> 2 | F13: 5
A14: EMP013 | B14: =VLOOKUP(A14,employee_master!A:B,2,FALSE) -> VEENA | C14: 26 | D14: 21 | E14: =C14-D14 -> 5 | F14: 7
... A16: EMP015 | B16: =VLOOKUP(A16,employee_master!A:B,2,FALSE) -> MAYUR | C16: 26 | D16: 25 | E16: =C16-D16 -> 1 | F16: 12

Sheet payroll
A1: employee id | B1: employee name | C1: department | D1: basic salary | E1: HRA | F1: bonus | G1: over time pay | H1: PF deductions | I1: tax deductions | J1: net salary
A2: EMP001 | B2: =VLOOKUP(A2,employee_master!A:B,2,FALSE) -> RAJIV | C2: =VLOOKUP(A2,employee_master!A:C,3,FALSE) -> Human Resources (HR) | D2: =VLOOKUP(A2,employee_master!A:F,6,FALSE) -> 85000 | E2: =D2*20% -> 17000 | F2: =IF(D2>=40000,3000,1500) -> 3000 | G2: =Attendance!F2*200 -> 1000 | H2: =D2*12% -> 10200 | I2: =D2*5% -> 4250 | J2: =D2+E2+F2+G2-H2-I2 -> 91550
A3: EMP002 | B3: =VLOOKUP(A3,employee_master!A:B,2,FALSE) -> NAGA | C3: =VLOOKUP(A3,employee_master!A:C,3,FALSE) -> Finance & Accounting | D3: =VLOOKUP(A3,employee_master!A:F,6,FALSE) -> 62500 | E3: =D3*20% -> 12500 | F3: =IF(D3>=40000,3000,1500) -> 3000 | G3: =Attendance!F3*200 -> 400 | H3: =D3*12% -> 7500 | I3: =D3*5% -> 3125 | J3: =D3+E3+F3+G3-H3-I3 -> 67775
A4: EMP003 | B4: =VLOOKUP(A4,employee_master!A:B,2,FALSE) -> WASIF | C4: =VLOOKUP(A4,employee_master!A:C,3,FALSE) -> Information Technology (IT) | D4: =VLOOKUP(A4,employee_master!A:F,6,FALSE) -> 45000 | E4: =D4*20% -> 9000 | F4: =IF(D4>=40000,3000,1500) -> 3000 | G4: =Attendance!F4*200 -> 2000 | H4: =D4*12% -> 5400 | I4: =D4*5% -> 2250 | J4: =D4+E4+F4+G4-H4-I4 -> 51350
A5: EMP004 | B5: =VLOOKUP(A5,employee_master!A:B,2,FALSE) -> RAJA | C5: =VLOOKUP(A5,employee_master!A:C,3,FALSE) -> Sales | D5: =VLOOKUP(A5,employee_master!A:F,6,FALSE) -> 120000 | E5: =D5*20% -> 24000 | F5: =IF(D5>=40000,3000,1500) -> 3000 | G5: =Attendance!F5*200 -> 400 | H5: =D5*12% -> 14400 | I5: =D5*5% -> 6000 | J5: =D5+E5+F5+G5-H5-I5 -> 127000
A6: EMP005 | B6: =VLOOKUP(A6,employee_master!A:B,2,FALSE) -> RAVI NAVI | C6: =VLOOKUP(A6,employee_master!A:C,3,FALSE) -> Marketing | D6: =VLOOKUP(A6,employee_master!A:F,6,FALSE) -> 55000 | E6: =D6*20% -> 11000 | F6: =IF(D6>=40000,3000,1500) -> 3000 | G6: =Attendance!F6*200 -> 2400 | H6: =D6*12% -> 6600 | I6: =D6*5% -> 2750 | J6: =D6+E6+F6+G6-H6-I6 -> 62050
A7: EMP006 | B7: =VLOOKUP(A7,employee_master!A:B,2,FALSE) -> SHREE | C7: =VLOOKUP(A7,employee_master!A:C,3,FALSE) -> Operations | D7: =VLOOKUP(A7,employee_master!A:F,6,FALSE) -> 78000 | E7: =D7*20% -> 15600 | F7: =IF(D7>=40000,3000,1500) -> 3000 | G7: =Attendance!F7*200 -> 1200 | H7: =D7*12% -> 9360 | I7: =D7*5% -> 3900 | J7: =D7+E7+F7+G7-H7-I7 -> 84540
A8: EMP007 | B8: =VLOOKUP(A8,employee_master!A:B,2,FALSE) -> KALESH | C8: =VLOOKUP(A8,employee_master!A:C,3,FALSE) -> Customer Support | D8: =VLOOKUP(A8,employee_master!A:F,6,FALSE) -> 35000 | E8: =D8*20% -> 7000 | F8: =IF(D8>=40000,3000,1500) -> 1500 | G8: =Attendance!F8*200 -> 600 | H8: =D8*12% -> 4200 | I8: =D8*5% -> 1750 | J8: =D8+E8+F8+G8-H8-I8 -> 38150
A9: EMP008 | B9: =VLOOKUP(A9,employee_master!A:B,2,FALSE) -> KHAANI | C9: =VLOOKUP(A9,employee_master!A:C,3,FALSE) -> Research & Development (R&D) | D9: =VLOOKUP(A9,employee_master!A:F,6,FALSE) -> 95000 | E9: =D9*20% -> 19000 | F9: =IF(D9>=40000,3000,1500) -> 3000 | G9: =Attendance!F9*200 -> 1400 | H9: =D9*12% -> 11400 | I9: =D9*5% -> 4750 | J9: =D9+E9+F9+G9-H9-I9 -> 102250
A10: EMP009 | B10: =VLOOKUP(A10,employee_master!A:B,2,FALSE) -> SHRIBA | C10: =VLOOKUP(A10,employee_master!A:C,3,FALSE) -> Legal & Compliance | D10: =VLOOKUP(A10,employee_master!A:F,6,FALSE) -> 50000 | E10: =D10*20% -> 10000 | F10: =IF(D10>=40000,3000,1500) -> 3000 | G10: =Attendance!F10*200 -> 1200 | H10: =D10*12% -> 6000 | I10: =D10*5% -> 2500 | J10: =D10+E10+F10+G10-H10-I10 -> 55700
A11: EMP010 | B11: =VLOOKUP(A11,employee_master!A:B,2,FALSE) -> MEDHA | C11: =VLOOKUP(A11,employee_master!A:C,3,FALSE) -> Supply Chain & Logistics | D11: =VLOOKUP(A11,employee_master!A:F,6,FALSE) -> 68000 | E11: =D11*20% -> 13600 | F11: =IF(D11>=40000,3000,1500) -> 3000 | G11: =Attendance!F11*200 -> 2000 | H11: =D11*12% -> 8160 | I11: =D11*5% -> 3400 | J11: =D11+E11+F11+G11-H11-I11 -> 75040
A12: EMP011 | B12: =VLOOKUP(A12,employee_master!A:B,2,FALSE) -> SHRIVANI | C12: =VLOOKUP(A12,employee_master!A:C,3,FALSE) -> Product Management | D12: =VLOOKUP(A12,employee_master!A:F,6,FALSE) -> 110000 | E12: =D12*20% -> 22000 | F12: =IF(D12>=40000,3000,1500) -> 3000 | G12: =Attendance!F12*200 -> 1600 | H12: =D12*12% -> 13200 | I12: =D12*5% -> 5500 | J12: =D12+E12+F12+G12-H12-I12 -> 117900
A13: EMP012 | B13: =VLOOKUP(A13,employee_master!A:B,2,FALSE) -> RAANI | C13: =VLOOKUP(A13,employee_master!A:C,3,FALSE) -> Quality Assurance (QA) | D13: =VLOOKUP(A13,employee_master!A:F,6,FALSE) -> 42000 | E13: =D13*20% -> 8400 | F13: =IF(D13>=40000,3000,1500) -> 3000 | G13: =Attendance!F13*200 -> 1000 | H13: =D13*12% -> 5040 | I13: =D13*5% -> 2100 | J13: =D13+E13+F13+G13-H13-I13 -> 47260
... A16: EMP015 | B16: =VLOOKUP(A16,employee_master!A:B,2,FALSE) -> MAYUR | C16: =VLOOKUP(A16,employee_master!A:C,3,FALSE) -> Administration / Facilities | D16: =VLOOKUP(A16,employee_master!A:F,6,FALSE) -> 89000 | E16: =D16*20% -> 17800 | F16: =IF(D16>=40000,3000,1500) -> 3000 | G16: =Attendance!F16*200 -> 2400 | H16: =D16*12% -> 10680 | I16: =D16*5% -> 4450 | J16: =D16+E16+F16+G16-H16-I16 -> 97070

Sheet Dashboard
A1: EMPLOYEE PAYROLL MANGEMENT DASHBOARD
A2: Total Employees | B2: =COUNTA(employee_master!A2:A16) -> 15
A3: Total Payroll Expense | B3: =SUM(payroll!J2:J16) -> 1160535 | H3: Row Labels | I3: Sum of net salary
A4: Average Salary | B4: =AVERAGE(payroll!J2:J16) -> 77369 | H4: Business Development | I4: 78760
A5: Highest Salary | B5: =MAX(payroll!J2:J16) -> 127000 | H5: Legal & Compliance | I5: 55700
H6: Marketing | I6: 62050
H7: Operations | I7: 84540
H8: Public Relations (PR) | I8: 64140
H9: Research & Development (R&D) | I9: 102250
H10: Sales | I10: 127000
H11: Administration / Facilities | I11: 97070
H12: Customer Support | I12: 38150
H13: Finance & Accounting | I13: 67775
H14: Human Resources (HR) | I14: 91550
H15: Information Technology (IT) | I15: 51350
H16: Product Management | I16: 117900
H17: Quality Assurance (QA) | I17: 47260
... H19: Grand Total | I19: 1160535
